libname/__init__.py
libname/scprel.py
libname/scprell.py
scprel/__init__.py
scprel/functions.py
scprel-1.3.dist-info/LICENSE.txt
scprel-1.3.dist-info/METADATA
scprel-1.3.dist-info/WHEEL
scprel-1.3.dist-info/top_level.txt
scprel-1.3.dist-info/RECORD
