Metadata-Version: 2.1
Name: scprel
Version: 1.3
Summary: Single-cell data preprocessing for multiple samples.
Home-page: https://pypi.org/project/scprel/
Author: GPuzanov (Grigory Puzanov)
Author-email: <grigorypuzanov@gmail.com>
License: UNKNOWN
Keywords: python,jupyter notebook,single-cell,scRNA-seq,single-cell quality control,single-cell data preparation,single-cell multiple samples,samples concatenation
Platform: UNKNOWN
Classifier: Development Status :: 1 - Planning
Classifier: Intended Audience :: Science/Research
Classifier: License :: OSI Approved :: MIT License
Classifier: Programming Language :: Python :: 3
Classifier: Programming Language :: Python :: 3.6
Classifier: Programming Language :: Python :: 3.7
Classifier: Programming Language :: Python :: 3.8
Classifier: Programming Language :: Python :: 3.9
Classifier: Operating System :: Unix
Classifier: Operating System :: MacOS :: MacOS X
Classifier: Operating System :: Microsoft :: Windows
Requires-Dist: omnipath
Requires-Dist: infercnvpy
Requires-Dist: anndata
Requires-Dist: decoupler
Requires-Dist: hdf5plugin
Requires-Dist: scanpy
Requires-Dist: scrublet
Requires-Dist: adjustText
Requires-Dist: wget
